MANIFEST.in
README.md
setup.py
easy_zipcode/__init__.py
easy_zipcode/main.py
easy_zipcode/urls.py
easy_zipcode/views.py
easy_zipcode.egg-info/PKG-INFO
easy_zipcode.egg-info/SOURCES.txt
easy_zipcode.egg-info/dependency_links.txt
easy_zipcode.egg-info/not-zip-safe
easy_zipcode.egg-info/requires.txt
easy_zipcode.egg-info/top_level.txt