Metadata-Version: 1.1
Name: easy-zipcode
Version: 0.1.5
Summary: easy_zipcode is a lightweight python app for retrieving         brazilian address from a zip code
Home-page: http://github.com/stored/easy_zipcode
Author: Fernando Chimicoviaki
Author-email: fernando.chimicoviaki@stored.com.br
License: BSD
Keywords: zip code
Platform: UNKNOWN
Classifier: Programming Language :: Python
Classifier: Framework :: Django
